[{"ts":"2025-09-05T08:39:37.086Z","id":"lsn50\r","fields":{"BatV":3.414,"TempC_SHT31":18.2,"Hum_SHT31":76.3}},{"ts":"2025-09-05T08:42:28.296Z","id":"s31\r","fields":{"TempC_SHT31":16.6,"BatV":3.612,"Hum_SHT31":99.4}},{"fields":{"water_SOIL":7.39,"BatV":3.326,"temp_SOIL":14.85},"id":"se01\r","ts":"2025-09-05T08:48:00.755Z"},{"ts":"2025-09-05T08:30:14.368Z","id":"kanzlei\r","fields":{"lon":10.1544934,"BatV":3.648,"lat":54.3369846}},{"id":"kropp\r","ts":"2025-09-05T08:45:34.318Z","fields":{"Hum_SHT":97.5,"BatV":3.636,"TempC_SHT":17.3}},{"ts":"2025-09-05T08:30:08.97Z","id":"fahrdorf\r","fields":{"Hum_SHT":97,"BatV":3.582,"TempC_SHT":17}},{"ts":"2025-09-05T08:41:18.9Z","id":"breklum\r","fields":{"TempC_SHT":25.3,"BatV":3.636,"Hum_SHT":58.4}},{"fields":{"lon":8.5464,"BatV":3.66,"lat":54.5582},"id":"hooge\r","ts":"2025-09-05T08:30:23.494Z"}]
