[{"ts":"2025-09-17T04:18:07.995Z","id":"breklum","fields":{"TempC_SHT":22.7,"Hum_SHT":60.5,"BatV":3.636}},{"fields":{"TempC_SHT":12,"Hum_SHT":93.3,"BatV":3.582},"id":"fahrdorf","ts":"2025-09-17T04:26:54.042Z"},{"fields":{"BatV":3.648,"lon":8.5464,"lat":54.5582},"id":"hooge","ts":"2025-09-17T04:35:30.142Z"},{"fields":{"lat":54.4093988908855,"lon":9.5285027323752,"BatV":3.636,"TempC_SHT":9.7,"Hum_SHT":99.4},"ts":"2025-09-17T04:22:27.726Z","id":"kropp"},{"fields":{"lat":54.4098456794914,"lon":9.52719737520844,"Hum_SHT31":81,"BatV":3.405,"TempC_SHT31":13.4},"ts":"2025-09-17T04:19:43.633Z","id":"lsn50"},{"fields":{"TempC_SHT":19.9,"Hum_SHT":59.3,"BatV":3.642,"lon":9.98926,"lat":54.07586},"id":"neumuenstertl","ts":"2025-09-17T03:32:22.458Z"},{"ts":"2025-09-17T04:19:31.934Z","id":"s31","fields":{"lat":54.651105744662,"lon":8.95686194107564,"Hum_SHT31":98.2,"TempC_SHT31":12.5,"BatV":3.606}}]
