[{"fields":{"Hum_SHT":66.4,"lon":8.98195,"lat":54.60669,"BatV":3.636,"TempC_SHT":23.3},"id":"breklum","ts":"2025-09-21T00:57:05.659Z"},{"ts":"2025-09-21T00:45:50.421Z","id":"fahrdorf","fields":{"TempC_SHT":17.9,"lon":9.5869,"BatV":3.582,"lat":54.50158,"Hum_SHT":94.2}},{"ts":"2025-09-21T00:54:48.873Z","id":"hooge","fields":{"lon":8.5464,"BatV":3.648,"lat":54.5582}},{"id":"kropp","fields":{"TempC_SHT":17.6,"Hum_SHT":94.2,"lon":9.5285027323752,"BatV":3.636,"lat":54.4093988908855},"ts":"2025-09-21T00:41:26.139Z"},{"fields":{"Hum_SHT":59.4,"lon":9.98926,"lat":54.07586,"BatV":3.636,"TempC_SHT":21.5},"id":"neumuenstertl","ts":"2025-09-21T00:51:03.434Z"},{"ts":"2025-09-21T00:58:34.157Z","fields":{"Hum_SHT":98.6,"lat":54.651105744662,"lon":8.95686194107564,"BatV":3.612,"Hum_SHT31":98.6,"TempC_SHT":17.6,"TempC_SHT31":17.6},"id":"s31"},{"ts":"2025-09-21T00:43:36.268Z","fields":{"water_SOIL":16.41,"BatV":3.326,"lon":8.95686197886804,"lat":54.6513978699169,"temp_SOIL":14.77},"id":"se01"}]
