[{"id":"breklum","ts":"2025-09-19T16:37:27.402Z","fields":{"lon":8.98195,"BatV":3.636,"Hum_SHT":63,"lat":54.60669,"TempC_SHT":24.5}},{"fields":{"TempC_SHT":19.8,"lat":54.50158,"Hum_SHT":85.9,"BatV":3.588,"lon":9.5869},"ts":"2025-09-19T16:46:12.459Z","id":"fahrdorf"},{"fields":{"lon":8.5464,"BatV":3.648,"lat":54.5582},"ts":"2025-09-19T16:55:14.332Z","id":"hooge"},{"id":"kropp","fields":{"lon":9.5285027323752,"BatV":3.636,"Hum_SHT":90.7,"lat":54.4093988908855,"TempC_SHT":18.7},"ts":"2025-09-19T16:41:47.269Z"},{"id":"neumuenstertl","ts":"2025-09-19T16:51:30.525Z","fields":{"lon":9.98926,"BatV":3.642,"Hum_SHT":60.1,"lat":54.07586,"TempC_SHT":21.7}},{"fields":{"lat":54.651105744662,"TempC_SHT":18.8,"lon":8.95686194107564,"BatV":3.612,"TempC_SHT31":18.8,"Hum_SHT31":89.8,"Hum_SHT":89.8},"ts":"2025-09-19T16:38:54.333Z","id":"s31"},{"id":"se01","fields":{"temp_SOIL":14.84,"water_SOIL":17,"lat":54.6513978699169,"BatV":3.326,"lon":8.95686197886804},"ts":"2025-09-19T16:43:58.838Z"}]
