[{"fields":{"Hum_SHT":58.5,"BatV":3.636,"lon":8.98195,"lat":54.60669,"TempC_SHT":24},"ts":"2025-09-17T16:17:59.921Z","id":"breklum"},{"ts":"2025-09-17T16:06:46.031Z","id":"fahrdorf","fields":{"Hum_SHT":77.9,"TempC_SHT":16.4,"lon":9.5869,"BatV":3.588,"lat":54.50158}},{"fields":{"lat":54.5582,"BatV":3.648,"lon":8.5464},"id":"hooge","ts":"2025-09-17T16:15:20.845Z"},{"fields":{"TempC_SHT":14.7,"lon":9.5285027323752,"BatV":3.636,"lat":54.4093988908855,"Hum_SHT":86.6},"ts":"2025-09-17T16:22:19.396Z","id":"kropp"},{"ts":"2025-09-17T10:59:43.829Z","id":"lsn50","fields":{"lat":54.4098456794914,"lon":9.52719737520844,"BatV":3.405,"Hum_SHT31":79.4,"TempC_SHT31":15.3}},{"fields":{"Hum_SHT":58.7,"lat":54.07586,"BatV":3.642,"lon":9.98926,"TempC_SHT":20.2},"ts":"2025-09-17T16:12:11.728Z","id":"neumuenstertl"},{"fields":{"TempC_SHT":16.1,"Hum_SHT31":78.6,"BatV":3.612,"lat":54.651105744662,"TempC_SHT31":15.5,"lon":8.95686194107564,"Hum_SHT":79.6},"id":"s31","ts":"2025-09-17T16:19:24.507Z"},{"fields":{"water_SOIL":8.87,"lat":54.6513978699169,"lon":8.95686197886804,"BatV":3.326,"temp_SOIL":13.72},"id":"se01","ts":"2025-09-17T16:04:33.147Z"}]
