[{"fields":{"TempC_SHT31":16,"Hum_SHT31":64.4,"lat":54.64988,"Hum_SHT":64.4,"BatV":3.612,"lon":8.955,"TempC_SHT":16},"ts":"2025-09-29T13:16:44.289Z","id":"bredstedt_s31lb"},{"id":"bredstedt_se01lb","ts":"2025-09-29T13:21:36.69Z","fields":{"water_SOIL":14.22,"lat":54.64988,"lon":8.957,"temp_SOIL":12.46,"BatV":3.326}},{"fields":{"lat":54.50158,"lon":9.5869,"Hum_SHT":62.6,"TempC_SHT":18.2,"BatV":3.588},"ts":"2025-09-29T13:23:31.356Z","id":"fahrdorf"},{"fields":{"BatV":3.636,"lon":9.92468,"lat":54.66205},"ts":"2025-09-29T13:09:09.961Z","id":"kappeln"},{"id":"kellinghusen_lsn50v2","ts":"2025-09-29T13:14:34.209Z","fields":{"lon":9.71426,"lat":53.95655,"Hum_SHT":54.3,"BatV":3.407,"TempC_SHT":24.2}},{"id":"kropp","ts":"2025-09-29T13:19:12.91Z","fields":{"Hum_SHT":61.5,"BatV":3.636,"TempC_SHT":16,"lon":9.5285027323752,"lat":54.4093988908855}},{"fields":{"lon":9.98926,"lat":54.07586,"BatV":3.642,"TempC_SHT":21,"Hum_SHT":54.1},"ts":"2025-09-29T13:08:10.395Z","id":"neumuenstertl"},{"id":"schacht_audorf","ts":"2025-09-29T13:19:34.887Z","fields":{"lon":9.7196,"lat":54.30687,"TempC_SHT":24.7,"BatV":3.636,"Hum_SHT":52.1}},{"fields":{"BatV":3.636},"ts":"2025-09-29T13:11:22.499Z","id":"test2"},{"fields":{"BatV":3.642},"ts":"2025-09-29T13:17:06.24Z","id":"test3"},{"fields":{"lat":54.02755,"lon":9.37503,"BatV":3.66},"id":"wacken","ts":"2025-09-29T13:14:31.249Z"}]
