[{"fields":{"Hum_SHT31":90,"lat":54.64988,"lon":8.955,"TempC_SHT31":11,"Hum_SHT":90,"BatV":3.606,"TempC_SHT":11},"id":"bredstedt_s31lb","ts":"2025-09-28T20:16:54.656Z"},{"ts":"2025-09-28T20:21:48.487Z","id":"bredstedt_se01lb","fields":{"temp_SOIL":12.8,"BatV":3.326,"water_SOIL":14.31,"lat":54.64988,"lon":8.957}},{"fields":{"lon":9.5869,"lat":54.50158,"TempC_SHT":12,"BatV":3.588,"Hum_SHT":89.7},"id":"fahrdorf","ts":"2025-09-28T20:23:42.85Z"},{"fields":{"BatV":3.636,"lon":9.92468,"lat":54.66205},"id":"kappeln","ts":"2025-09-28T20:09:23.527Z"},{"fields":{"Hum_SHT":54,"BatV":3.407,"TempC_SHT":23.6,"lat":53.95655,"lon":9.71426},"id":"kellinghusen_lsn50v2","ts":"2025-09-28T20:14:34.102Z"},{"ts":"2025-09-28T20:19:23.904Z","id":"kropp","fields":{"BatV":3.636,"TempC_SHT":8.7,"lat":54.4093988908855,"lon":9.5285027323752,"Hum_SHT":91.5}},{"fields":{"Hum_SHT":54.4,"lon":9.98926,"lat":54.07586,"TempC_SHT":21.2,"BatV":3.642},"id":"neumuenstertl","ts":"2025-09-28T19:08:25.611Z"},{"id":"schacht_audorf","ts":"2025-09-28T20:19:46.325Z","fields":{"Hum_SHT":53.9,"lat":54.30687,"lon":9.7196,"BatV":3.636,"TempC_SHT":23.4}},{"fields":{"BatV":3.636},"ts":"2025-09-28T20:11:34.694Z","id":"test2"},{"id":"test3","ts":"2025-09-28T20:17:17.757Z","fields":{"BatV":3.642}},{"ts":"2025-09-28T20:14:43.127Z","id":"wacken","fields":{"lon":9.37503,"lat":54.02755,"BatV":3.66}}]
