[{"id":"breklum","fields":{"TempC_SHT":22.6,"BatV":3.636,"lon":8.98195,"Hum_SHT":54.7,"lat":54.60669},"ts":"2025-09-24T09:45:17.352Z"},{"id":"fahrdorf","ts":"2025-09-24T18:04:49.889Z","fields":{"lat":54.50158,"Hum_SHT":73.7,"lon":9.5869,"BatV":3.582,"TempC_SHT":12.3}},{"id":"hooge","ts":"2025-09-24T10:13:44.139Z","fields":{"BatV":3.642,"lon":8.5464,"lat":54.5582}},{"fields":{"lon":9.5285027323752,"lat":54.4093988908855,"Hum_SHT":85.6,"TempC_SHT":7.9,"BatV":3.63},"ts":"2025-09-24T18:20:27.969Z","id":"kropp"},{"id":"neumuenstertl","fields":{"Hum_SHT":56.8,"lat":54.07586,"lon":9.98926,"BatV":3.636,"TempC_SHT":21.7},"ts":"2025-09-24T18:09:47.817Z"},{"ts":"2025-09-24T18:17:39.531Z","fields":{"lat":54.651105744662,"Hum_SHT":77.5,"lon":8.95686194107564,"TempC_SHT31":11,"BatV":3.606,"Hum_SHT31":77.5,"TempC_SHT":11},"id":"s31"},{"fields":{"lon":9.7196,"Hum_SHT":53.4,"lat":54.30687,"TempC_SHT":24.1,"BatV":3.624},"ts":"2025-09-24T18:06:03.399Z","id":"schacht_audorf"},{"id":"se01","fields":{"BatV":3.326,"lat":54.6513978699169,"temp_SOIL":12.73,"lon":8.95686197886804,"water_SOIL":15.35},"ts":"2025-09-24T18:02:34.176Z"}]
