[{"id":"breklum","ts":"2025-09-16T16:18:16.064Z","fields":{"BatV":3.636,"TempC_SHT":23.5,"Hum_SHT":59.6}},{"fields":{"Hum_SHT":98.5,"TempC_SHT":13.8,"BatV":3.588},"ts":"2025-09-16T16:27:02.186Z","id":"fahrdorf"},{"id":"hooge","ts":"2025-09-16T16:15:39.953Z","fields":{"BatV":3.648,"lon":8.5464,"lat":54.5582}},{"id":"kropp","ts":"2025-09-16T16:22:35.119Z","fields":{"BatV":3.636,"TempC_SHT":13,"Hum_SHT":99.4,"lat":54.4093988908855,"lon":9.5285027323752}},{"id":"lsn50","ts":"2025-09-16T16:19:43.258Z","fields":{"TempC_SHT31":16,"BatV":3.407,"lat":54.4098456794914,"Hum_SHT31":80.7,"lon":9.52719737520844}},{"id":"neumuenstertl","fields":{"lon":9.98926,"lat":54.07586,"TempC_SHT":20.3,"BatV":3.642,"Hum_SHT":61.6},"ts":"2025-09-16T16:12:32.034Z"},{"id":"s31","ts":"2025-09-16T16:19:39.327Z","fields":{"lat":54.651105744662,"lon":8.95686194107564,"Hum_SHT31":100,"TempC_SHT31":13.7,"BatV":3.606}}]
