[{"ts":"2025-10-01T08:56:17.684Z","id":"bredstedt_s31lb","fields":{"Hum_SHT":81.5,"lon":8.955,"BatV":3.606,"TempC_SHT31":10.2,"Hum_SHT31":81.5,"lat":54.64988,"TempC_SHT":10.2}},{"ts":"2025-10-01T09:01:06.422Z","id":"bredstedt_se01lb","fields":{"lat":54.64988,"temp_SOIL":11.59,"BatV":3.326,"lon":8.957,"water_SOIL":13.94}},{"ts":"2025-10-01T09:03:01.922Z","id":"fahrdorf","fields":{"lon":9.5869,"Hum_SHT":80.1,"BatV":3.582,"TempC_SHT":11.4,"lat":54.50158}},{"ts":"2025-10-01T08:48:35.151Z","id":"kappeln","fields":{"lat":54.66205,"BatV":3.642,"lon":9.92468}},{"ts":"2025-10-01T08:54:33.953Z","fields":{"Hum_SHT":47.1,"lon":9.71426,"BatV":3.405,"lat":53.95655,"TempC_SHT":21.6},"id":"kellinghusen_lsn50v2"},{"ts":"2025-10-01T08:58:44.814Z","id":"kropp","fields":{"Hum_SHT":83.6,"lon":9.5285027323752,"lat":54.4093988908855,"TempC_SHT":10,"BatV":3.63}},{"ts":"2025-10-01T08:47:33.386Z","id":"neumuenstertl","fields":{"Hum_SHT":53.4,"lon":9.98926,"lat":54.07586,"TempC_SHT":20.7,"BatV":3.642}},{"id":"schacht_audorf","fields":{"lon":9.7196,"Hum_SHT":49.9,"BatV":3.636,"TempC_SHT":21.1,"lat":54.30687},"ts":"2025-10-01T08:59:05.485Z"},{"id":"test2","fields":{"BatV":3.636},"ts":"2025-10-01T08:50:51.187Z"},{"ts":"2025-10-01T08:56:36.651Z","fields":{"BatV":3.642},"id":"test3"},{"fields":{"lon":9.37503,"BatV":3.66,"lat":54.02755},"id":"wacken","ts":"2025-10-01T08:54:00.705Z"}]
