[{"ts":"2025-09-30T12:36:29.979Z","id":"bredstedt_s31lb","fields":{"lat":54.64988,"Hum_SHT":71.4,"BatV":3.606,"lon":8.955,"TempC_SHT31":14.7,"Hum_SHT31":71.4,"TempC_SHT":14.7}},{"fields":{"lon":8.957,"temp_SOIL":12.41,"lat":54.64988,"water_SOIL":14.03,"BatV":3.326},"ts":"2025-09-30T12:41:20.435Z","id":"bredstedt_se01lb"},{"id":"fahrdorf","ts":"2025-09-30T12:43:15.502Z","fields":{"Hum_SHT":74.5,"BatV":3.582,"lat":54.50158,"TempC_SHT":14.2,"lon":9.5869}},{"fields":{"lon":9.92468,"BatV":3.642,"lat":54.66205},"ts":"2025-09-30T12:28:51.363Z","id":"kappeln"},{"id":"kellinghusen_lsn50v2","ts":"2025-09-30T12:34:34.353Z","fields":{"BatV":3.409,"Hum_SHT":53,"lat":53.95655,"TempC_SHT":23.9,"lon":9.71426}},{"ts":"2025-09-30T12:38:57.759Z","id":"kropp","fields":{"lat":54.4093988908855,"Hum_SHT":80.2,"BatV":3.636,"lon":9.5285027323752,"TempC_SHT":14}},{"ts":"2025-09-30T12:47:50.34Z","id":"neumuenstertl","fields":{"BatV":3.642,"Hum_SHT":53.9,"lat":54.07586,"TempC_SHT":20.9,"lon":9.98926}},{"id":"schacht_audorf","ts":"2025-09-30T12:39:19.176Z","fields":{"lat":54.30687,"Hum_SHT":52.3,"BatV":3.636,"lon":9.7196,"TempC_SHT":24.5}},{"fields":{"BatV":3.636},"id":"test2","ts":"2025-09-30T12:31:05.774Z"},{"id":"test3","ts":"2025-09-30T12:36:50.433Z","fields":{"BatV":3.642}},{"ts":"2025-09-30T12:34:14.925Z","id":"wacken","fields":{"lat":54.02755,"BatV":3.66,"lon":9.37503}}]
