[{"ts":"2025-09-30T03:36:35.488Z","fields":{"Hum_SHT":97.1,"TempC_SHT":9.8,"lon":8.955,"lat":54.64988,"BatV":3.606,"TempC_SHT31":9.8,"Hum_SHT31":97.1},"id":"bredstedt_s31lb"},{"ts":"2025-09-30T03:41:26.698Z","fields":{"water_SOIL":14.05,"temp_SOIL":12.34,"BatV":3.326,"lat":54.64988,"lon":8.957},"id":"bredstedt_se01lb"},{"id":"fahrdorf","ts":"2025-09-30T03:43:21.607Z","fields":{"lon":9.5869,"BatV":3.582,"lat":54.50158,"TempC_SHT":10.4,"Hum_SHT":92.2}},{"fields":{"lat":54.66205,"BatV":3.636,"lon":9.92468},"ts":"2025-09-30T03:28:58.539Z","id":"kappeln"},{"fields":{"Hum_SHT":55,"lon":9.71426,"lat":53.95655,"TempC_SHT":24.2,"BatV":3.412},"ts":"2025-09-30T03:34:34.289Z","id":"kellinghusen_lsn50v2"},{"id":"kropp","ts":"2025-09-30T03:39:03.586Z","fields":{"lon":9.5285027323752,"BatV":3.636,"TempC_SHT":6.5,"lat":54.4093988908855,"Hum_SHT":93.8}},{"ts":"2025-09-30T03:27:58.232Z","fields":{"lon":9.98926,"TempC_SHT":20.9,"lat":54.07586,"BatV":3.636,"Hum_SHT":53.9},"id":"neumuenstertl"},{"ts":"2025-09-30T03:39:25.224Z","fields":{"TempC_SHT":24,"lat":54.30687,"BatV":3.63,"lon":9.7196,"Hum_SHT":56.3},"id":"schacht_audorf"},{"id":"test2","ts":"2025-09-30T03:31:12.22Z","fields":{"BatV":3.636}},{"id":"test3","fields":{"BatV":3.642},"ts":"2025-09-30T03:36:56.527Z"},{"ts":"2025-09-30T03:34:21.218Z","fields":{"lon":9.37503,"lat":54.02755,"BatV":3.66},"id":"wacken"}]
