{
  "node": "se01lb_bredstedt",
  "position": {
    "lat": 54.64988,
    "lon": 8.957
  },
  "time": "2025-10-23T01:55:46.888760Z",
  "gateways": [
    {
      "id": "eui-7076ff0056070bb4",
      "rssi": -108.0,
      "snr": 0.2
    },
    {
      "id": "eui-00007076ff031372",
      "rssi": -108.0,
      "snr": 0.2
    }
  ],
  "values": {
    "BatV": 3.326,
    "rx_time1": "2025-10-23T01:55:46.608Z",
    "sf": 7.0,
    "snr1": 0.2,
    "snr2": 0.2,
    "temp_SOIL": 11.09,
    "water_SOIL": 14.5
  }
}