{
  "node": "se01lb",
  "position": {
    "lat": 54.64988,
    "lon": 8.957
  },
  "time": "2025-05-04T16:22:55.579554Z",
  "gateways": [
    {
      "id": "eui-00007076ff031372",
      "rssi": -105.0,
      "snr": 6.5
    },
    {
      "id": "eui-7076ff0056070bb4",
      "rssi": -105.0,
      "snr": 6.5
    }
  ],
  "values": {
    "BatV": 3.326,
    "alt1": 0.0,
    "alt2": 0.0,
    "chan1": 2.0,
    "freq1": 0.0,
    "gw1": "eui-00007076ff031372",
    "gw2": "eui-7076ff0056070bb4",
    "lat1": 0.0,
    "lat2": 0.0,
    "lon1": 0.0,
    "lon2": 0.0,
    "rssi1": -105.0,
    "rssi2": -105.0,
    "rx_time1": "2025-05-04T16:22:55.283Z",
    "sf": 7.0,
    "snr1": 6.5,
    "snr2": 6.5,
    "temp_SOIL": 8.72,
    "water_SOIL": 9.74
  }
}