{
  "node": "se01lb_bredstedt",
  "position": {
    "lat": 54.64988,
    "lon": 8.957
  },
  "time": "2025-10-08T13:39:48.286474Z",
  "gateways": [
    {
      "id": "eui-7076ff0056070bb4",
      "rssi": -112.0,
      "snr": 6.8
    },
    {
      "id": "eui-00007076ff031358",
      "rssi": -112.0,
      "snr": 6.8
    }
  ],
  "values": {
    "BatV": 3.326,
    "rx_time1": "2025-10-08T13:39:47.993Z",
    "sf": 7.0,
    "snr1": 6.8,
    "snr2": 6.8,
    "temp_SOIL": 12.69,
    "water_SOIL": 17.56
  }
}