[
  {
    "ts": "2025-09-27T04:22:17.987Z",
    "fields": {
      "lon": 8.95686,
      "lat": 54.651105,
      "BatV": 3.582
    },
    "id": "bredstedt_se01lb"
  },
  {
    "id": "bredstedt_se01lb",
    "ts": "2025-09-27T04:42:16.478Z",
    "fields": {
      "lon": 8.95686,
      "lat": 54.651105,
      "BatV": 3.582
    }
  },
  {
    "id": "bredstedt_se01lb",
    "fields": {
      "lon": 8.95686,
      "BatV": 3.582,
      "lat": 54.651105
    },
    "ts": "2025-09-27T05:02:16.192Z"
  },
  {
    "ts": "2025-09-27T05:22:15.983Z",
    "fields": {
      "lon": 8.95686,
      "lat": 54.651105,
      "BatV": 3.582
    },
    "id": "bredstedt_se01lb"
  },
  {
    "fields": {
      "lon": 8.95686,
      "BatV": 3.582,
      "lat": 54.651105
    },
    "ts": "2025-09-27T05:42:15.744Z",
    "id": "bredstedt_se01lb"
  },
  {
    "ts": "2025-09-27T06:02:15.531Z",
    "id": "bredstedt_se01lb",
    "fields": {
      "BatV": 3.582,
      "lon": 8.95686,
      "lat": 54.651105
    }
  },
  {
    "fields": {
      "lat": 54.651105,
      "BatV": 3.582,
      "lon": 8.95686
    },
    "id": "bredstedt_se01lb",
    "ts": "2025-09-27T06:22:15.292Z"
  },
  {
    "ts": "2025-09-27T06:42:15.051Z",
    "id": "bredstedt_se01lb",
    "fields": {
      "BatV": 3.582,
      "lon": 8.95686,
      "lat": 54.651105
    }
  },
  {
    "ts": "2025-09-27T07:02:14.947Z",
    "fields": {
      "lat": 54.651105,
      "BatV": 3.582,
      "lon": 8.95686
    },
    "id": "bredstedt_se01lb"
  },
  {
    "ts": "2025-09-27T07:22:14.489Z",
    "id": "bredstedt_se01lb",
    "fields": {
      "lon": 8.95686,
      "BatV": 3.582,
      "lat": 54.651105
    }
  },
  {
    "fields": {
      "BatV": 3.582,
      "lat": 54.651105,
      "lon": 8.95686
    },
    "ts": "2025-09-27T07:42:14.265Z",
    "id": "bredstedt_se01lb"
  },
  {
    "ts": "2025-09-27T08:02:14.031Z",
    "fields": {
      "BatV": 3.582,
      "lat": 54.651105,
      "lon": 8.95686
    },
    "id": "bredstedt_se01lb"
  },
  {
    "ts": "2025-09-27T08:22:13.788Z",
    "fields": {
      "BatV": 3.582,
      "lon": 8.95686,
      "lat": 54.651105
    },
    "id": "bredstedt_se01lb"
  },
  {
    "id": "bredstedt_se01lb",
    "ts": "2025-09-27T08:42:13.565Z",
    "fields": {
      "lon": 8.95686,
      "lat": 54.651105,
      "temp_SOIL": 12.44,
      "BatV": 3.326,
      "water_SOIL": 14.64
    }
  },
  {
    "id": "bredstedt_se01lb",
    "ts": "2025-09-27T09:02:13.337Z",
    "fields": {
      "water_SOIL": 14.64,
      "temp_SOIL": 12.45,
      "lat": 54.651105,
      "BatV": 3.326,
      "lon": 8.95686
    }
  },
  {
    "ts": "2025-09-27T09:22:13.098Z",
    "id": "bredstedt_se01lb",
    "fields": {
      "temp_SOIL": 12.47,
      "water_SOIL": 14.63,
      "BatV": 3.326,
      "lat": 54.651105,
      "lon": 8.95686
    }
  },
  {
    "fields": {
      "lat": 54.651105,
      "water_SOIL": 14.63,
      "temp_SOIL": 12.49,
      "BatV": 3.326,
      "lon": 8.95686
    },
    "id": "bredstedt_se01lb",
    "ts": "2025-09-27T09:42:12.861Z"
  },
  {
    "ts": "2025-09-27T10:02:12.615Z",
    "id": "bredstedt_se01lb",
    "fields": {
      "lon": 8.95686,
      "BatV": 3.326,
      "temp_SOIL": 12.51,
      "water_SOIL": 14.62,
      "lat": 54.651105
    }
  },
  {
    "fields": {
      "water_SOIL": 14.62,
      "BatV": 3.326,
      "lon": 8.95686,
      "lat": 54.651105,
      "temp_SOIL": 12.51
    },
    "id": "bredstedt_se01lb",
    "ts": "2025-09-27T10:22:12.39Z"
  },
  {
    "ts": "2025-09-27T10:42:12.15Z",
    "fields": {
      "lon": 8.957,
      "lat": 54.64988,
      "temp_SOIL": 12.52,
      "BatV": 3.326,
      "water_SOIL": 14.61
    },
    "id": "bredstedt_se01lb"
  },
  {
    "fields": {
      "BatV": 3.326,
      "temp_SOIL": 12.53,
      "water_SOIL": 14.62,
      "lat": 54.64988,
      "lon": 8.957
    },
    "id": "bredstedt_se01lb",
    "ts": "2025-09-27T11:02:11.931Z"
  },
  {
    "fields": {
      "water_SOIL": 14.61,
      "lon": 8.957,
      "temp_SOIL": 12.54,
      "BatV": 3.326,
      "lat": 54.64988
    },
    "id": "bredstedt_se01lb",
    "ts": "2025-09-27T11:22:11.69Z"
  },
  {
    "id": "bredstedt_se01lb",
    "ts": "2025-09-27T11:42:11.449Z",
    "fields": {
      "lon": 8.957,
      "water_SOIL": 14.61,
      "lat": 54.64988,
      "BatV": 3.326,
      "temp_SOIL": 12.57
    }
  },
  {
    "fields": {
      "water_SOIL": 14.61,
      "BatV": 3.326,
      "temp_SOIL": 12.59,
      "lat": 54.64988,
      "lon": 8.957
    },
    "ts": "2025-09-27T12:02:11.206Z",
    "id": "bredstedt_se01lb"
  },
  {
    "ts": "2025-09-27T12:22:10.995Z",
    "fields": {
      "temp_SOIL": 12.61,
      "lat": 54.64988,
      "water_SOIL": 14.61,
      "lon": 8.957,
      "BatV": 3.326
    },
    "id": "bredstedt_se01lb"
  },
  {
    "ts": "2025-09-27T12:42:10.769Z",
    "id": "bredstedt_se01lb",
    "fields": {
      "temp_SOIL": 12.62,
      "water_SOIL": 14.6,
      "BatV": 3.326,
      "lat": 54.64988,
      "lon": 8.957
    }
  },
  {
    "fields": {
      "water_SOIL": 14.61,
      "temp_SOIL": 12.63,
      "lat": 54.64988,
      "BatV": 3.326,
      "lon": 8.957
    },
    "id": "bredstedt_se01lb",
    "ts": "2025-09-27T13:02:10.511Z"
  },
  {
    "fields": {
      "water_SOIL": 14.6,
      "lon": 8.957,
      "temp_SOIL": 12.64,
      "BatV": 3.326,
      "lat": 54.64988
    },
    "id": "bredstedt_se01lb",
    "ts": "2025-09-27T13:22:10.265Z"
  },
  {
    "ts": "2025-09-27T13:42:10.056Z",
    "id": "bredstedt_se01lb",
    "fields": {
      "temp_SOIL": 12.67,
      "lon": 8.957,
      "lat": 54.64988,
      "BatV": 3.326,
      "water_SOIL": 14.59
    }
  },
  {
    "id": "bredstedt_se01lb",
    "ts": "2025-09-27T14:02:09.817Z",
    "fields": {
      "BatV": 3.326,
      "lon": 8.957,
      "lat": 54.64988,
      "water_SOIL": 14.58,
      "temp_SOIL": 12.69
    }
  },
  {
    "id": "bredstedt_se01lb",
    "ts": "2025-09-27T14:22:09.576Z",
    "fields": {
      "temp_SOIL": 12.71,
      "water_SOIL": 14.58,
      "BatV": 3.326,
      "lon": 8.957,
      "lat": 54.64988
    }
  },
  {
    "ts": "2025-09-27T14:42:09.359Z",
    "fields": {
      "BatV": 3.326,
      "water_SOIL": 14.58,
      "lat": 54.64988,
      "lon": 8.957,
      "temp_SOIL": 12.72
    },
    "id": "bredstedt_se01lb"
  },
  {
    "id": "bredstedt_se01lb",
    "ts": "2025-09-27T15:02:09.104Z",
    "fields": {
      "lat": 54.64988,
      "temp_SOIL": 12.72,
      "lon": 8.957,
      "water_SOIL": 14.59,
      "BatV": 3.326
    }
  },
  {
    "id": "bredstedt_se01lb",
    "fields": {
      "lon": 8.957,
      "temp_SOIL": 12.73,
      "water_SOIL": 14.59,
      "lat": 54.64988,
      "BatV": 3.326
    },
    "ts": "2025-09-27T15:22:08.87Z"
  },
  {
    "fields": {
      "temp_SOIL": 12.74,
      "lon": 8.957,
      "lat": 54.64988,
      "BatV": 3.326,
      "water_SOIL": 14.55
    },
    "ts": "2025-09-27T15:42:08.628Z",
    "id": "bredstedt_se01lb"
  },
  {
    "fields": {
      "lat": 54.64988,
      "lon": 8.957,
      "water_SOIL": 14.55,
      "temp_SOIL": 12.75,
      "BatV": 3.326
    },
    "ts": "2025-09-27T16:02:08.409Z",
    "id": "bredstedt_se01lb"
  },
  {
    "id": "bredstedt_se01lb",
    "ts": "2025-09-27T16:22:08.145Z",
    "fields": {
      "BatV": 3.326,
      "water_SOIL": 14.55,
      "lat": 54.64988,
      "temp_SOIL": 12.76,
      "lon": 8.957
    }
  },
  {
    "fields": {
      "temp_SOIL": 12.76,
      "lon": 8.957,
      "water_SOIL": 14.54,
      "lat": 54.64988,
      "BatV": 3.326
    },
    "ts": "2025-09-27T16:42:07.925Z",
    "id": "bredstedt_se01lb"
  },
  {
    "ts": "2025-09-27T17:02:07.691Z",
    "fields": {
      "temp_SOIL": 12.76,
      "lon": 8.957,
      "water_SOIL": 14.56,
      "lat": 54.64988,
      "BatV": 3.326
    },
    "id": "bredstedt_se01lb"
  },
  {
    "ts": "2025-09-27T17:22:07.444Z",
    "fields": {
      "water_SOIL": 14.52,
      "lat": 54.64988,
      "temp_SOIL": 12.76,
      "BatV": 3.326,
      "lon": 8.957
    },
    "id": "bredstedt_se01lb"
  },
  {
    "fields": {
      "temp_SOIL": 12.76,
      "lon": 8.957,
      "water_SOIL": 14.54,
      "BatV": 3.326,
      "lat": 54.64988
    },
    "ts": "2025-09-27T17:42:07.234Z",
    "id": "bredstedt_se01lb"
  },
  {
    "id": "bredstedt_se01lb",
    "fields": {
      "temp_SOIL": 12.75,
      "lon": 8.957,
      "BatV": 3.326,
      "lat": 54.64988,
      "water_SOIL": 14.56
    },
    "ts": "2025-09-27T18:02:06.956Z"
  },
  {
    "id": "bredstedt_se01lb",
    "fields": {
      "temp_SOIL": 12.74,
      "lon": 8.957,
      "BatV": 3.326,
      "lat": 54.64988,
      "water_SOIL": 14.51
    },
    "ts": "2025-09-27T18:22:06.702Z"
  },
  {
    "id": "bredstedt_se01lb",
    "fields": {
      "lon": 8.957,
      "lat": 54.64988,
      "temp_SOIL": 12.73,
      "BatV": 3.326,
      "water_SOIL": 14.55
    },
    "ts": "2025-09-27T18:42:06.479Z"
  },
  {
    "fields": {
      "water_SOIL": 14.55,
      "lon": 8.957,
      "temp_SOIL": 12.73,
      "BatV": 3.326,
      "lat": 54.64988
    },
    "id": "bredstedt_se01lb",
    "ts": "2025-09-27T19:02:06.25Z"
  },
  {
    "ts": "2025-09-27T19:22:06.009Z",
    "fields": {
      "lat": 54.64988,
      "BatV": 3.326,
      "water_SOIL": 14.5,
      "lon": 8.957,
      "temp_SOIL": 12.73
    },
    "id": "bredstedt_se01lb"
  },
  {
    "ts": "2025-09-27T19:42:05.763Z",
    "id": "bredstedt_se01lb",
    "fields": {
      "lat": 54.64988,
      "BatV": 3.326,
      "water_SOIL": 14.5,
      "lon": 8.957,
      "temp_SOIL": 12.73
    }
  },
  {
    "fields": {
      "lat": 54.64988,
      "lon": 8.957,
      "water_SOIL": 14.49,
      "BatV": 3.326,
      "temp_SOIL": 12.73
    },
    "id": "bredstedt_se01lb",
    "ts": "2025-09-27T20:02:05.528Z"
  },
  {
    "id": "bredstedt_se01lb",
    "fields": {
      "water_SOIL": 14.5,
      "temp_SOIL": 12.72,
      "lat": 54.64988,
      "BatV": 3.326,
      "lon": 8.957
    },
    "ts": "2025-09-27T20:22:05.31Z"
  },
  {
    "fields": {
      "lat": 54.64988,
      "lon": 8.957,
      "water_SOIL": 14.49,
      "BatV": 3.326,
      "temp_SOIL": 12.72
    },
    "ts": "2025-09-27T20:42:05.065Z",
    "id": "bredstedt_se01lb"
  },
  {
    "fields": {
      "water_SOIL": 14.5,
      "BatV": 3.326,
      "temp_SOIL": 12.72,
      "lat": 54.64988,
      "lon": 8.957
    },
    "id": "bredstedt_se01lb",
    "ts": "2025-09-27T21:02:04.847Z"
  },
  {
    "fields": {
      "lon": 8.957,
      "BatV": 3.326,
      "lat": 54.64988,
      "water_SOIL": 14.46,
      "temp_SOIL": 12.72
    },
    "id": "bredstedt_se01lb",
    "ts": "2025-09-27T21:22:04.609Z"
  },
  {
    "id": "bredstedt_se01lb",
    "ts": "2025-09-27T21:42:04.363Z",
    "fields": {
      "lat": 54.64988,
      "temp_SOIL": 12.72,
      "water_SOIL": 14.51,
      "BatV": 3.326,
      "lon": 8.957
    }
  },
  {
    "fields": {
      "BatV": 3.326,
      "lat": 54.64988,
      "water_SOIL": 14.49,
      "lon": 8.957,
      "temp_SOIL": 12.72
    },
    "ts": "2025-09-27T22:02:04.135Z",
    "id": "bredstedt_se01lb"
  },
  {
    "id": "bredstedt_se01lb",
    "fields": {
      "water_SOIL": 14.46,
      "lon": 8.957,
      "BatV": 3.326,
      "temp_SOIL": 12.72,
      "lat": 54.64988
    },
    "ts": "2025-09-27T22:22:03.904Z"
  },
  {
    "ts": "2025-09-27T22:42:03.674Z",
    "fields": {
      "temp_SOIL": 12.72,
      "lon": 8.957,
      "water_SOIL": 14.48,
      "BatV": 3.326,
      "lat": 54.64988
    },
    "id": "bredstedt_se01lb"
  },
  {
    "ts": "2025-09-27T23:02:03.426Z",
    "fields": {
      "water_SOIL": 14.46,
      "BatV": 3.326,
      "lat": 54.64988,
      "lon": 8.957,
      "temp_SOIL": 12.72
    },
    "id": "bredstedt_se01lb"
  },
  {
    "fields": {
      "lat": 54.64988,
      "water_SOIL": 14.45,
      "BatV": 3.326,
      "lon": 8.957,
      "temp_SOIL": 12.72
    },
    "id": "bredstedt_se01lb",
    "ts": "2025-09-27T23:22:03.211Z"
  },
  {
    "ts": "2025-09-27T23:42:02.967Z",
    "fields": {
      "temp_SOIL": 12.72,
      "lat": 54.64988,
      "lon": 8.957,
      "water_SOIL": 14.47,
      "BatV": 3.326
    },
    "id": "bredstedt_se01lb"
  },
  {
    "ts": "2025-09-28T00:02:02.756Z",
    "fields": {
      "water_SOIL": 14.44,
      "lon": 8.957,
      "BatV": 3.326,
      "lat": 54.64988,
      "temp_SOIL": 12.72
    },
    "id": "bredstedt_se01lb"
  },
  {
    "ts": "2025-09-28T00:22:02.506Z",
    "id": "bredstedt_se01lb",
    "fields": {
      "BatV": 3.326,
      "temp_SOIL": 12.72,
      "lon": 8.957,
      "water_SOIL": 14.46,
      "lat": 54.64988
    }
  },
  {
    "id": "bredstedt_se01lb",
    "fields": {
      "temp_SOIL": 12.72,
      "water_SOIL": 14.46,
      "lon": 8.957,
      "lat": 54.64988,
      "BatV": 3.326
    },
    "ts": "2025-09-28T00:42:02.277Z"
  },
  {
    "ts": "2025-09-28T01:02:02.04Z",
    "id": "bredstedt_se01lb",
    "fields": {
      "lon": 8.957,
      "lat": 54.64988,
      "water_SOIL": 14.42,
      "temp_SOIL": 12.72,
      "BatV": 3.326
    }
  },
  {
    "ts": "2025-09-28T01:22:01.808Z",
    "id": "bredstedt_se01lb",
    "fields": {
      "lat": 54.64988,
      "BatV": 3.326,
      "water_SOIL": 14.43,
      "temp_SOIL": 12.72,
      "lon": 8.957
    }
  },
  {
    "ts": "2025-09-28T01:42:01.575Z",
    "fields": {
      "water_SOIL": 14.45,
      "lat": 54.64988,
      "BatV": 3.326,
      "lon": 8.957,
      "temp_SOIL": 12.72
    },
    "id": "bredstedt_se01lb"
  },
  {
    "id": "bredstedt_se01lb",
    "ts": "2025-09-28T02:02:01.332Z",
    "fields": {
      "water_SOIL": 14.45,
      "BatV": 3.326,
      "lon": 8.957,
      "lat": 54.64988,
      "temp_SOIL": 12.72
    }
  },
  {
    "fields": {
      "water_SOIL": 14.46,
      "BatV": 3.326,
      "lon": 8.957,
      "lat": 54.64988,
      "temp_SOIL": 12.72
    },
    "id": "bredstedt_se01lb",
    "ts": "2025-09-28T02:22:01.112Z"
  },
  {
    "id": "bredstedt_se01lb",
    "ts": "2025-09-28T02:42:00.866Z",
    "fields": {
      "temp_SOIL": 12.72,
      "BatV": 3.326,
      "lat": 54.64988,
      "lon": 8.957,
      "water_SOIL": 14.42
    }
  },
  {
    "fields": {
      "BatV": 3.326,
      "water_SOIL": 14.41,
      "lat": 54.64988,
      "lon": 8.957,
      "temp_SOIL": 12.71
    },
    "ts": "2025-09-28T03:02:00.631Z",
    "id": "bredstedt_se01lb"
  },
  {
    "ts": "2025-09-28T03:22:00.408Z",
    "id": "bredstedt_se01lb",
    "fields": {
      "lat": 54.64988,
      "temp_SOIL": 12.71,
      "BatV": 3.326,
      "lon": 8.957,
      "water_SOIL": 14.42
    }
  },
  {
    "id": "bredstedt_se01lb",
    "fields": {
      "BatV": 3.326,
      "lon": 8.957,
      "water_SOIL": 14.41,
      "temp_SOIL": 12.7,
      "lat": 54.64988
    },
    "ts": "2025-09-28T03:42:00.163Z"
  },
  {
    "id": "bredstedt_se01lb",
    "ts": "2025-09-28T04:01:59.944Z",
    "fields": {
      "temp_SOIL": 12.69,
      "lat": 54.64988,
      "BatV": 3.326,
      "water_SOIL": 14.43,
      "lon": 8.957
    }
  },
  {
    "fields": {
      "lat": 54.64988,
      "water_SOIL": 14.42,
      "lon": 8.957,
      "temp_SOIL": 12.67,
      "BatV": 3.326
    },
    "id": "bredstedt_se01lb",
    "ts": "2025-09-28T04:21:59.703Z"
  },
  {
    "id": "bredstedt_se01lb",
    "ts": "2025-09-28T04:41:59.483Z",
    "fields": {
      "BatV": 3.326,
      "lat": 54.64988,
      "lon": 8.957,
      "water_SOIL": 14.43,
      "temp_SOIL": 12.65
    }
  },
  {
    "id": "bredstedt_se01lb",
    "fields": {
      "temp_SOIL": 12.64,
      "water_SOIL": 14.44,
      "BatV": 3.326,
      "lon": 8.957,
      "lat": 54.64988
    },
    "ts": "2025-09-28T05:01:59.238Z"
  },
  {
    "id": "bredstedt_se01lb",
    "fields": {
      "lat": 54.64988,
      "lon": 8.957,
      "water_SOIL": 14.43,
      "BatV": 3.326,
      "temp_SOIL": 12.62
    },
    "ts": "2025-09-28T05:21:59.015Z"
  },
  {
    "fields": {
      "lat": 54.64988,
      "lon": 8.957,
      "BatV": 3.326,
      "water_SOIL": 14.42,
      "temp_SOIL": 12.62
    },
    "id": "bredstedt_se01lb",
    "ts": "2025-09-28T05:41:58.794Z"
  },
  {
    "ts": "2025-09-28T06:01:58.528Z",
    "fields": {
      "temp_SOIL": 12.61,
      "water_SOIL": 14.43,
      "BatV": 3.326,
      "lon": 8.957,
      "lat": 54.64988
    },
    "id": "bredstedt_se01lb"
  },
  {
    "ts": "2025-09-28T06:21:58.319Z",
    "id": "bredstedt_se01lb",
    "fields": {
      "temp_SOIL": 12.59,
      "lat": 54.64988,
      "lon": 8.957,
      "water_SOIL": 14.42,
      "BatV": 3.326
    }
  },
  {
    "ts": "2025-09-28T06:41:58.093Z",
    "fields": {
      "water_SOIL": 14.44,
      "lat": 54.64988,
      "lon": 8.957,
      "BatV": 3.326,
      "temp_SOIL": 12.57
    },
    "id": "bredstedt_se01lb"
  },
  {
    "fields": {
      "water_SOIL": 14.43,
      "temp_SOIL": 12.55,
      "lat": 54.64988,
      "lon": 8.957,
      "BatV": 3.326
    },
    "id": "bredstedt_se01lb",
    "ts": "2025-09-28T07:01:57.882Z"
  },
  {
    "ts": "2025-09-28T07:21:57.628Z",
    "fields": {
      "BatV": 3.326,
      "water_SOIL": 14.43,
      "temp_SOIL": 12.54,
      "lon": 8.957,
      "lat": 54.64988
    },
    "id": "bredstedt_se01lb"
  },
  {
    "id": "bredstedt_se01lb",
    "fields": {
      "BatV": 3.326,
      "temp_SOIL": 12.54,
      "lat": 54.64988,
      "lon": 8.957,
      "water_SOIL": 14.42
    },
    "ts": "2025-09-28T07:41:57.394Z"
  },
  {
    "ts": "2025-09-28T08:01:57.14Z",
    "fields": {
      "lat": 54.64988,
      "BatV": 3.326,
      "water_SOIL": 14.42,
      "temp_SOIL": 12.54,
      "lon": 8.957
    },
    "id": "bredstedt_se01lb"
  },
  {
    "fields": {
      "lat": 54.64988,
      "lon": 8.957,
      "water_SOIL": 14.42,
      "temp_SOIL": 12.54,
      "BatV": 3.326
    },
    "id": "bredstedt_se01lb",
    "ts": "2025-09-28T08:21:56.924Z"
  },
  {
    "id": "bredstedt_se01lb",
    "fields": {
      "lon": 8.957,
      "temp_SOIL": 12.55,
      "BatV": 3.326,
      "lat": 54.64988,
      "water_SOIL": 14.42
    },
    "ts": "2025-09-28T08:41:56.689Z"
  },
  {
    "fields": {
      "water_SOIL": 14.42,
      "temp_SOIL": 12.57,
      "lat": 54.64988,
      "lon": 8.957,
      "BatV": 3.326
    },
    "id": "bredstedt_se01lb",
    "ts": "2025-09-28T09:01:56.447Z"
  },
  {
    "id": "bredstedt_se01lb",
    "fields": {
      "lat": 54.64988,
      "BatV": 3.326,
      "lon": 8.957,
      "water_SOIL": 14.42,
      "temp_SOIL": 12.59
    },
    "ts": "2025-09-28T09:21:56.224Z"
  },
  {
    "fields": {
      "lat": 54.64988,
      "temp_SOIL": 12.61,
      "lon": 8.957,
      "BatV": 3.326,
      "water_SOIL": 14.41
    },
    "ts": "2025-09-28T09:41:55.997Z",
    "id": "bredstedt_se01lb"
  },
  {
    "fields": {
      "water_SOIL": 14.41,
      "lat": 54.64988,
      "BatV": 3.326,
      "temp_SOIL": 12.62,
      "lon": 8.957
    },
    "id": "bredstedt_se01lb",
    "ts": "2025-09-28T10:01:55.758Z"
  },
  {
    "ts": "2025-09-28T10:21:55.518Z",
    "fields": {
      "lon": 8.957,
      "lat": 54.64988,
      "BatV": 3.326,
      "temp_SOIL": 12.62,
      "water_SOIL": 14.41
    },
    "id": "bredstedt_se01lb"
  },
  {
    "ts": "2025-09-28T10:41:55.301Z",
    "id": "bredstedt_se01lb",
    "fields": {
      "BatV": 3.326,
      "temp_SOIL": 12.64,
      "water_SOIL": 14.41,
      "lat": 54.64988,
      "lon": 8.957
    }
  },
  {
    "id": "bredstedt_se01lb",
    "ts": "2025-09-28T11:01:55.054Z",
    "fields": {
      "BatV": 3.326,
      "temp_SOIL": 12.66,
      "lon": 8.957,
      "lat": 54.64988,
      "water_SOIL": 14.4
    }
  },
  {
    "id": "bredstedt_se01lb",
    "fields": {
      "water_SOIL": 14.41,
      "BatV": 3.326,
      "lon": 8.957,
      "temp_SOIL": 12.69,
      "lat": 54.64988
    },
    "ts": "2025-09-28T11:21:54.809Z"
  },
  {
    "id": "bredstedt_se01lb",
    "fields": {
      "water_SOIL": 14.4,
      "BatV": 3.326,
      "lon": 8.957,
      "temp_SOIL": 12.71,
      "lat": 54.64988
    },
    "ts": "2025-09-28T11:41:54.577Z"
  },
  {
    "ts": "2025-09-28T12:01:54.359Z",
    "fields": {
      "lon": 8.957,
      "lat": 54.64988,
      "temp_SOIL": 12.72,
      "water_SOIL": 14.38,
      "BatV": 3.326
    },
    "id": "bredstedt_se01lb"
  },
  {
    "fields": {
      "water_SOIL": 14.39,
      "lon": 8.957,
      "lat": 54.64988,
      "BatV": 3.326,
      "temp_SOIL": 12.73
    },
    "ts": "2025-09-28T12:21:54.111Z",
    "id": "bredstedt_se01lb"
  },
  {
    "fields": {
      "temp_SOIL": 12.75,
      "BatV": 3.326,
      "lon": 8.957,
      "lat": 54.64988,
      "water_SOIL": 14.36
    },
    "ts": "2025-09-28T12:41:53.865Z",
    "id": "bredstedt_se01lb"
  },
  {
    "ts": "2025-09-28T13:01:53.635Z",
    "fields": {
      "BatV": 3.326,
      "water_SOIL": 14.39,
      "lat": 54.64988,
      "temp_SOIL": 12.78,
      "lon": 8.957
    },
    "id": "bredstedt_se01lb"
  },
  {
    "id": "bredstedt_se01lb",
    "fields": {
      "water_SOIL": 14.37,
      "BatV": 3.326,
      "temp_SOIL": 12.81,
      "lat": 54.64988,
      "lon": 8.957
    },
    "ts": "2025-09-28T13:21:53.392Z"
  },
  {
    "ts": "2025-09-28T13:41:53.204Z",
    "id": "bredstedt_se01lb",
    "fields": {
      "lat": 54.64988,
      "lon": 8.957,
      "BatV": 3.326,
      "water_SOIL": 14.39,
      "temp_SOIL": 12.82
    }
  },
  {
    "id": "bredstedt_se01lb",
    "fields": {
      "lon": 8.957,
      "BatV": 3.326,
      "lat": 54.64988,
      "water_SOIL": 14.36,
      "temp_SOIL": 12.83
    },
    "ts": "2025-09-28T14:01:52.917Z"
  },
  {
    "ts": "2025-09-28T14:21:52.719Z",
    "fields": {
      "water_SOIL": 14.37,
      "lat": 54.64988,
      "lon": 8.957,
      "BatV": 3.326,
      "temp_SOIL": 12.84
    },
    "id": "bredstedt_se01lb"
  },
  {
    "id": "bredstedt_se01lb",
    "ts": "2025-09-28T14:41:52.448Z",
    "fields": {
      "lat": 54.64988,
      "water_SOIL": 14.32,
      "temp_SOIL": 12.85,
      "BatV": 3.326,
      "lon": 8.957
    }
  },
  {
    "id": "bredstedt_se01lb",
    "fields": {
      "lon": 8.957,
      "water_SOIL": 14.35,
      "temp_SOIL": 12.87,
      "BatV": 3.326,
      "lat": 54.64988
    },
    "ts": "2025-09-28T15:01:52.217Z"
  },
  {
    "ts": "2025-09-28T15:21:52.005Z",
    "id": "bredstedt_se01lb",
    "fields": {
      "water_SOIL": 14.34,
      "lat": 54.64988,
      "temp_SOIL": 12.88,
      "BatV": 3.326,
      "lon": 8.957
    }
  },
  {
    "id": "bredstedt_se01lb",
    "fields": {
      "lat": 54.64988,
      "water_SOIL": 14.3,
      "lon": 8.957,
      "BatV": 3.326,
      "temp_SOIL": 12.9
    },
    "ts": "2025-09-28T15:41:51.745Z"
  },
  {
    "fields": {
      "temp_SOIL": 12.91,
      "lon": 8.957,
      "water_SOIL": 14.33,
      "lat": 54.64988,
      "BatV": 3.326
    },
    "ts": "2025-09-28T16:01:51.531Z",
    "id": "bredstedt_se01lb"
  },
  {
    "fields": {
      "BatV": 3.326,
      "water_SOIL": 14.31,
      "lat": 54.64988,
      "lon": 8.957,
      "temp_SOIL": 12.91
    },
    "id": "bredstedt_se01lb",
    "ts": "2025-09-28T16:21:51.286Z"
  },
  {
    "id": "bredstedt_se01lb",
    "ts": "2025-09-28T16:41:51.051Z",
    "fields": {
      "temp_SOIL": 12.91,
      "lat": 54.64988,
      "lon": 8.957,
      "BatV": 3.326,
      "water_SOIL": 14.35
    }
  },
  {
    "fields": {
      "temp_SOIL": 12.91,
      "lon": 8.957,
      "BatV": 3.326,
      "lat": 54.64988,
      "water_SOIL": 14.34
    },
    "id": "bredstedt_se01lb",
    "ts": "2025-09-28T17:01:50.811Z"
  },
  {
    "ts": "2025-09-28T17:21:50.6Z",
    "id": "bredstedt_se01lb",
    "fields": {
      "temp_SOIL": 12.91,
      "lon": 8.957,
      "lat": 54.64988,
      "BatV": 3.326,
      "water_SOIL": 14.33
    }
  },
  {
    "fields": {
      "lat": 54.64988,
      "lon": 8.957,
      "water_SOIL": 14.29,
      "temp_SOIL": 12.91,
      "BatV": 3.326
    },
    "id": "bredstedt_se01lb",
    "ts": "2025-09-28T17:41:50.354Z"
  },
  {
    "id": "bredstedt_se01lb",
    "ts": "2025-09-28T18:01:50.109Z",
    "fields": {
      "lat": 54.64988,
      "water_SOIL": 14.29,
      "lon": 8.957,
      "temp_SOIL": 12.9,
      "BatV": 3.326
    }
  },
  {
    "fields": {
      "water_SOIL": 14.33,
      "lon": 8.957,
      "temp_SOIL": 12.88,
      "lat": 54.64988,
      "BatV": 3.326
    },
    "id": "bredstedt_se01lb",
    "ts": "2025-09-28T18:21:49.87Z"
  },
  {
    "ts": "2025-09-28T18:41:49.65Z",
    "id": "bredstedt_se01lb",
    "fields": {
      "BatV": 3.326,
      "water_SOIL": 14.29,
      "temp_SOIL": 12.86,
      "lat": 54.64988,
      "lon": 8.957
    }
  },
  {
    "ts": "2025-09-28T19:01:49.412Z",
    "fields": {
      "lat": 54.64988,
      "lon": 8.957,
      "BatV": 3.326,
      "temp_SOIL": 12.84,
      "water_SOIL": 14.29
    },
    "id": "bredstedt_se01lb"
  },
  {
    "ts": "2025-09-28T19:21:49.178Z",
    "fields": {
      "temp_SOIL": 12.83,
      "BatV": 3.326,
      "lat": 54.64988,
      "lon": 8.957,
      "water_SOIL": 14.33
    },
    "id": "bredstedt_se01lb"
  },
  {
    "fields": {
      "water_SOIL": 14.3,
      "lon": 8.957,
      "lat": 54.64988,
      "temp_SOIL": 12.82,
      "BatV": 3.326
    },
    "id": "bredstedt_se01lb",
    "ts": "2025-09-28T19:41:48.952Z"
  },
  {
    "id": "bredstedt_se01lb",
    "ts": "2025-09-28T20:01:48.721Z",
    "fields": {
      "lat": 54.64988,
      "BatV": 3.326,
      "temp_SOIL": 12.81,
      "water_SOIL": 14.31,
      "lon": 8.957
    }
  },
  {
    "fields": {
      "water_SOIL": 14.31,
      "temp_SOIL": 12.8,
      "lat": 54.64988,
      "lon": 8.957,
      "BatV": 3.326
    },
    "id": "bredstedt_se01lb",
    "ts": "2025-09-28T20:21:48.487Z"
  },
  {
    "ts": "2025-09-28T20:41:48.245Z",
    "fields": {
      "lat": 54.64988,
      "lon": 8.957,
      "water_SOIL": 14.32,
      "temp_SOIL": 12.77,
      "BatV": 3.326
    },
    "id": "bredstedt_se01lb"
  },
  {
    "id": "bredstedt_se01lb",
    "fields": {
      "lon": 8.957,
      "temp_SOIL": 12.75,
      "BatV": 3.326,
      "lat": 54.64988,
      "water_SOIL": 14.3
    },
    "ts": "2025-09-28T21:01:48.038Z"
  },
  {
    "fields": {
      "water_SOIL": 14.28,
      "BatV": 3.326,
      "lat": 54.64988,
      "lon": 8.957,
      "temp_SOIL": 12.73
    },
    "id": "bredstedt_se01lb",
    "ts": "2025-09-28T21:21:47.796Z"
  },
  {
    "ts": "2025-09-28T21:41:47.565Z",
    "fields": {
      "water_SOIL": 14.31,
      "lat": 54.64988,
      "lon": 8.957,
      "temp_SOIL": 12.72,
      "BatV": 3.326
    },
    "id": "bredstedt_se01lb"
  },
  {
    "ts": "2025-09-28T22:01:47.331Z",
    "fields": {
      "BatV": 3.326,
      "temp_SOIL": 12.71,
      "lon": 8.957,
      "water_SOIL": 14.3,
      "lat": 54.64988
    },
    "id": "bredstedt_se01lb"
  },
  {
    "ts": "2025-09-28T22:21:47.088Z",
    "fields": {
      "BatV": 3.326,
      "temp_SOIL": 12.69,
      "lat": 54.64988,
      "water_SOIL": 14.28,
      "lon": 8.957
    },
    "id": "bredstedt_se01lb"
  },
  {
    "fields": {
      "BatV": 3.326,
      "temp_SOIL": 12.66,
      "lat": 54.64988,
      "water_SOIL": 14.33,
      "lon": 8.957
    },
    "id": "bredstedt_se01lb",
    "ts": "2025-09-28T22:41:46.871Z"
  },
  {
    "id": "bredstedt_se01lb",
    "fields": {
      "water_SOIL": 14.28,
      "BatV": 3.326,
      "lon": 8.957,
      "lat": 54.64988,
      "temp_SOIL": 12.64
    },
    "ts": "2025-09-28T23:01:46.628Z"
  },
  {
    "fields": {
      "lat": 54.64988,
      "water_SOIL": 14.29,
      "BatV": 3.326,
      "temp_SOIL": 12.62,
      "lon": 8.957
    },
    "ts": "2025-09-28T23:21:46.406Z",
    "id": "bredstedt_se01lb"
  },
  {
    "fields": {
      "lon": 8.957,
      "lat": 54.64988,
      "BatV": 3.326,
      "temp_SOIL": 12.61,
      "water_SOIL": 14.33
    },
    "ts": "2025-09-28T23:41:46.164Z",
    "id": "bredstedt_se01lb"
  },
  {
    "id": "bredstedt_se01lb",
    "fields": {
      "water_SOIL": 14.32,
      "lat": 54.64988,
      "BatV": 3.326,
      "lon": 8.957,
      "temp_SOIL": 12.6
    },
    "ts": "2025-09-29T00:01:45.926Z"
  },
  {
    "ts": "2025-09-29T00:21:45.719Z",
    "id": "bredstedt_se01lb",
    "fields": {
      "BatV": 3.326,
      "lon": 8.957,
      "temp_SOIL": 12.57,
      "water_SOIL": 14.31,
      "lat": 54.64988
    }
  },
  {
    "ts": "2025-09-29T00:41:45.497Z",
    "id": "bredstedt_se01lb",
    "fields": {
      "temp_SOIL": 12.53,
      "lon": 8.957,
      "BatV": 3.326,
      "lat": 54.64988,
      "water_SOIL": 14.29
    }
  },
  {
    "ts": "2025-09-29T01:01:45.251Z",
    "fields": {
      "temp_SOIL": 12.52,
      "lat": 54.64988,
      "BatV": 3.326,
      "water_SOIL": 14.32,
      "lon": 8.957
    },
    "id": "bredstedt_se01lb"
  },
  {
    "ts": "2025-09-29T01:21:45.01Z",
    "fields": {
      "temp_SOIL": 12.51,
      "lon": 8.957,
      "BatV": 3.326,
      "lat": 54.64988,
      "water_SOIL": 14.31
    },
    "id": "bredstedt_se01lb"
  },
  {
    "id": "bredstedt_se01lb",
    "ts": "2025-09-29T01:41:44.792Z",
    "fields": {
      "lat": 54.64988,
      "lon": 8.957,
      "water_SOIL": 14.28,
      "BatV": 3.326,
      "temp_SOIL": 12.49
    }
  },
  {
    "ts": "2025-09-29T02:01:44.548Z",
    "fields": {
      "temp_SOIL": 12.47,
      "water_SOIL": 14.32,
      "BatV": 3.326,
      "lon": 8.957,
      "lat": 54.64988
    },
    "id": "bredstedt_se01lb"
  },
  {
    "id": "bredstedt_se01lb",
    "ts": "2025-09-29T02:21:44.332Z",
    "fields": {
      "water_SOIL": 14.31,
      "BatV": 3.326,
      "temp_SOIL": 12.43,
      "lat": 54.64988,
      "lon": 8.957
    }
  },
  {
    "fields": {
      "lat": 54.64988,
      "water_SOIL": 14.29,
      "lon": 8.957,
      "BatV": 3.326,
      "temp_SOIL": 12.42
    },
    "ts": "2025-09-29T02:41:44.105Z",
    "id": "bredstedt_se01lb"
  },
  {
    "id": "bredstedt_se01lb",
    "fields": {
      "lon": 8.957,
      "temp_SOIL": 12.41,
      "water_SOIL": 14.28,
      "lat": 54.64988,
      "BatV": 3.326
    },
    "ts": "2025-09-29T03:01:43.868Z"
  },
  {
    "fields": {
      "lat": 54.64988,
      "lon": 8.957,
      "BatV": 3.326,
      "temp_SOIL": 12.4,
      "water_SOIL": 14.27
    },
    "ts": "2025-09-29T03:21:43.629Z",
    "id": "bredstedt_se01lb"
  },
  {
    "id": "bredstedt_se01lb",
    "fields": {
      "water_SOIL": 14.31,
      "lon": 8.957,
      "lat": 54.64988,
      "BatV": 3.326,
      "temp_SOIL": 12.37
    },
    "ts": "2025-09-29T03:41:43.407Z"
  },
  {
    "fields": {
      "lat": 54.64988,
      "temp_SOIL": 12.35,
      "lon": 8.957,
      "BatV": 3.326,
      "water_SOIL": 14.29
    },
    "id": "bredstedt_se01lb",
    "ts": "2025-09-29T04:01:43.186Z"
  },
  {
    "ts": "2025-09-29T04:21:42.949Z",
    "fields": {
      "temp_SOIL": 12.33,
      "lon": 8.957,
      "lat": 54.64988,
      "water_SOIL": 14.27,
      "BatV": 3.326
    },
    "id": "bredstedt_se01lb"
  },
  {
    "fields": {
      "lat": 54.64988,
      "temp_SOIL": 12.32,
      "water_SOIL": 14.27,
      "BatV": 3.326,
      "lon": 8.957
    },
    "ts": "2025-09-29T04:41:42.727Z",
    "id": "bredstedt_se01lb"
  },
  {
    "fields": {
      "BatV": 3.326,
      "temp_SOIL": 12.31,
      "lat": 54.64988,
      "lon": 8.957,
      "water_SOIL": 14.26
    },
    "ts": "2025-09-29T05:01:42.48Z",
    "id": "bredstedt_se01lb"
  },
  {
    "id": "bredstedt_se01lb",
    "ts": "2025-09-29T05:21:42.278Z",
    "fields": {
      "lat": 54.64988,
      "lon": 8.957,
      "temp_SOIL": 12.3,
      "BatV": 3.326,
      "water_SOIL": 14.3
    }
  },
  {
    "ts": "2025-09-29T05:41:42.056Z",
    "id": "bredstedt_se01lb",
    "fields": {
      "temp_SOIL": 12.28,
      "water_SOIL": 14.26,
      "BatV": 3.326,
      "lat": 54.64988,
      "lon": 8.957
    }
  },
  {
    "id": "bredstedt_se01lb",
    "fields": {
      "lon": 8.957,
      "water_SOIL": 14.3,
      "temp_SOIL": 12.26,
      "BatV": 3.326,
      "lat": 54.64988
    },
    "ts": "2025-09-29T06:01:41.807Z"
  },
  {
    "fields": {
      "lat": 54.64988,
      "BatV": 3.326,
      "water_SOIL": 14.27,
      "temp_SOIL": 12.23,
      "lon": 8.957
    },
    "id": "bredstedt_se01lb",
    "ts": "2025-09-29T06:21:41.601Z"
  },
  {
    "fields": {
      "temp_SOIL": 12.22,
      "lat": 54.64988,
      "BatV": 3.326,
      "lon": 8.957,
      "water_SOIL": 14.26
    },
    "ts": "2025-09-29T06:41:41.344Z",
    "id": "bredstedt_se01lb"
  },
  {
    "id": "bredstedt_se01lb",
    "fields": {
      "lon": 8.957,
      "temp_SOIL": 12.21,
      "BatV": 3.326,
      "water_SOIL": 14.28,
      "lat": 54.64988
    },
    "ts": "2025-09-29T07:01:41.106Z"
  },
  {
    "fields": {
      "lat": 54.64988,
      "temp_SOIL": 12.2,
      "water_SOIL": 14.26,
      "BatV": 3.326,
      "lon": 8.957
    },
    "id": "bredstedt_se01lb",
    "ts": "2025-09-29T07:21:40.881Z"
  },
  {
    "ts": "2025-09-29T07:41:40.68Z",
    "id": "bredstedt_se01lb",
    "fields": {
      "water_SOIL": 14.26,
      "lat": 54.64988,
      "BatV": 3.326,
      "lon": 8.957,
      "temp_SOIL": 12.19
    }
  },
  {
    "id": "bredstedt_se01lb",
    "fields": {
      "water_SOIL": 14.25,
      "temp_SOIL": 12.19,
      "lat": 54.64988,
      "lon": 8.957,
      "BatV": 3.326
    },
    "ts": "2025-09-29T08:01:40.438Z"
  },
  {
    "id": "bredstedt_se01lb",
    "ts": "2025-09-29T08:21:40.197Z",
    "fields": {
      "lat": 54.64988,
      "water_SOIL": 14.26,
      "BatV": 3.326,
      "temp_SOIL": 12.18,
      "lon": 8.957
    }
  },
  {
    "id": "bredstedt_se01lb",
    "ts": "2025-09-29T08:41:39.969Z",
    "fields": {
      "lon": 8.957,
      "water_SOIL": 14.25,
      "BatV": 3.326,
      "temp_SOIL": 12.18,
      "lat": 54.64988
    }
  },
  {
    "ts": "2025-09-29T09:01:39.726Z",
    "id": "bredstedt_se01lb",
    "fields": {
      "temp_SOIL": 12.19,
      "lat": 54.64988,
      "water_SOIL": 14.25,
      "BatV": 3.326,
      "lon": 8.957
    }
  },
  {
    "id": "bredstedt_se01lb",
    "ts": "2025-09-29T09:21:39.495Z",
    "fields": {
      "temp_SOIL": 12.2,
      "lat": 54.64988,
      "water_SOIL": 14.26,
      "lon": 8.957,
      "BatV": 3.326
    }
  },
  {
    "fields": {
      "lon": 8.957,
      "BatV": 3.326,
      "lat": 54.64988,
      "temp_SOIL": 12.21,
      "water_SOIL": 14.24
    },
    "ts": "2025-09-29T09:41:39.27Z",
    "id": "bredstedt_se01lb"
  },
  {
    "id": "bredstedt_se01lb",
    "fields": {
      "BatV": 3.326,
      "water_SOIL": 14.25,
      "temp_SOIL": 12.21,
      "lat": 54.64988,
      "lon": 8.957
    },
    "ts": "2025-09-29T10:01:39.025Z"
  }
]
